arthcalculator/__init__.py
arthcalculator-0.1.dist-info/LICENSE.txt
arthcalculator-0.1.dist-info/METADATA
arthcalculator-0.1.dist-info/WHEEL
arthcalculator-0.1.dist-info/top_level.txt
arthcalculator-0.1.dist-info/RECORD
