Metadata-Version: 2.1
Name: arthcalculator
Version: 0.1
Summary: Basic arthmetics calculator
Home-page: UNKNOWN
Author: Murali Mohan
Author-email: 
License: MIT
Keywords: calculator
Platform: UNKNOWN
Classifier: Development Status :: 5 - Production/Stable
Classifier: Intended Audience :: Education
Classifier: Operating System :: Microsoft :: Windows :: Windows 10
Classifier: License :: OSI Approved :: MIT License
Classifier: Programming Language :: Python :: 3
License-File: LICENSE.txt
